tests
trellotool
