Metadata-Version: 2.1
Name: trellotool
Version: 0.0.3
Summary: A CLI for trello
Home-page: https://github.com/mrda/trellotool
Author: Michael Davies
Author-email: michael@the-davies.net
License: GNU General Public License v3
Download-URL: https://github.com/mrda/trellotool/archive/0.0.3.tar.gz
Platform: UNKNOWN
Classifier: Programming Language :: Python :: 3
Classifier: License :: OSI Approved :: GNU General Public License v3 or later (GPLv3+)
Classifier: Operating System :: OS Independent
